elevation/__init__.py
elevation/conf.py
elevation/data.py
elevation/KG_ELEVATION/elevation_Kyrgyzstan_2023.nc
elevation_Kyrgyzstan-1.0.0.dist-info/METADATA
elevation_Kyrgyzstan-1.0.0.dist-info/WHEEL
elevation_Kyrgyzstan-1.0.0.dist-info/top_level.txt
elevation_Kyrgyzstan-1.0.0.dist-info/RECORD
