Metadata-Version: 2.1
Name: elevation-Kyrgyzstan
Version: 1.0.0
Summary: Get the elevation of any ground point in Kyrgyzstan with Elevation-Kyrgyzstan
Home-page: https://github.com/Azim-Kenzh/elevation-Kyrgyzstan
Author: Azimkozho Kenzhebek uulu
Author-email: azimkozho.inventor@gmail.com
Classifier: Development Status :: 1 - Planning
Classifier: Environment :: Console
Classifier: Intended Audience :: Developers
Classifier: Operating System :: OS Independent
Classifier: Programming Language :: Python
Requires-Dist: xarray
Requires-Dist: netCDF4
